video_silence_remover_mcp/__init__.py
video_silence_remover_mcp/main.py
mcpcn_video_silence_remover_mcp-0.1.4.dist-info/METADATA
mcpcn_video_silence_remover_mcp-0.1.4.dist-info/WHEEL
mcpcn_video_silence_remover_mcp-0.1.4.dist-info/entry_points.txt
mcpcn_video_silence_remover_mcp-0.1.4.dist-info/RECORD
