Metadata-Version: 2.4
Name: mcpcn-video-silence-remover-mcp
Version: 0.1.4
Summary: MCP server for removing silent segments from audio/video files
Author-email: Your Name <your.email@example.com>
License: MIT
Keywords: audio,ffmpeg,mcp,removal,silence,video
Classifier: Development Status :: 4 - Beta
Classifier: Intended Audience :: Developers
Classifier: License :: OSI Approved :: MIT License
Classifier: Programming Language :: Python :: 3
Classifier: Programming Language :: Python :: 3.12
Classifier: Topic :: Multimedia :: Sound/Audio
Classifier: Topic :: Multimedia :: Video
Classifier: Topic :: Software Development :: Libraries :: Python Modules
Requires-Python: >=3.12
Requires-Dist: ffmpeg-python>=0.2.0
Requires-Dist: mcp[cli]>=1.9.0
